matwerber_awscdk_constructs/__init__.py
matwerber_awscdk_constructs/py.typed
matwerber_awscdk_constructs/_jsii/__init__.py
matwerber_awscdk_constructs/_jsii/awscdk-constructs@0.0.1.jsii.tgz
matwerber_awscdk_constructs-0.0.1.dist-info/LICENSE
matwerber_awscdk_constructs-0.0.1.dist-info/METADATA
matwerber_awscdk_constructs-0.0.1.dist-info/WHEEL
matwerber_awscdk_constructs-0.0.1.dist-info/top_level.txt
matwerber_awscdk_constructs-0.0.1.dist-info/RECORD
